{
  "timestamp": "2026-01-03T19:14:44.534752",
  "total": 8,
  "channels": [
    {
      "name": "CCTV-1 综合",
      "url": "http://39.135.55.105:6610/PLTV/88888910/224/3221225618/index.m3u8",
      "timestamp": "2026-01-03T19:14:44.534337"
    },
    {
      "name": "CCTV-2 财经",
      "url": "http://39.135.55.105:6610/PLTV/88888910/224/3221225619/index.m3u8",
      "timestamp": "2026-01-03T19:14:44.534349"
    },
    {
      "name": "CCTV-3 综艺",
      "url": "http://39.135.55.105:6610/PLTV/88888910/224/3221225620/index.m3u8",
      "timestamp": "2026-01-03T19:14:44.534352"
    },
    {
      "name": "CCTV-4 国际",
      "url": "http://39.135.55.105:6610/PLTV/88888910/224/3221225621/index.m3u8",
      "timestamp": "2026-01-03T19:14:44.534355"
    },
    {
      "name": "CCTV-5 体育",
      "url": "http://39.135.55.105:6610/PLTV/88888910/224/3221225622/index.m3u8",
      "timestamp": "2026-01-03T19:14:44.534358"
    },
    {
      "name": "浙江卫视",
      "url": "http://39.135.55.105:6610/PLTV/88888910/224/3221225814/index.m3u8",
      "timestamp": "2026-01-03T19:14:44.534360"
    },
    {
      "name": "江苏卫视",
      "url": "http://39.135.55.105:6610/PLTV/88888910/224/3221225815/index.m3u8",
      "timestamp": "2026-01-03T19:14:44.534363"
    },
    {
      "name": "湖南卫视",
      "url": "http://39.135.55.105:6610/PLTV/88888910/224/3221225816/index.m3u8",
      "timestamp": "2026-01-03T19:14:44.534366"
    }
  ]
}